kdai_node_client/__init__.py
kdai_node_client/cli.py
kdai_node_client/exceptions.py
kdai_node_client/node.py
kdai_node_client/tasks.py
kdai_node_client/utils.py
kdai_node_client/version.py
kdai_node_client-0.2.3.dist-info/LICENSE
kdai_node_client-0.2.3.dist-info/METADATA
kdai_node_client-0.2.3.dist-info/WHEEL
kdai_node_client-0.2.3.dist-info/entry_points.txt
kdai_node_client-0.2.3.dist-info/top_level.txt
kdai_node_client-0.2.3.dist-info/RECORD
