Metadata-Version: 2.1
Name: kdai-node-client
Version: 0.2.3
Summary: Client library for connecting nodes to the KDAI distributed AI platform
Home-page: https://github.com/kdai-io/kdai-node-client
Author: KDAI Team
Author-email: KDAI Team <support@kdai.io>
License: MIT
Project-URL: Homepage, https://github.com/kdai-io/kdai-node-client
Project-URL: Bug Tracker, https://github.com/kdai-io/kdai-node-client/issues
Classifier: Programming Language :: Python :: 3
Classifier: Programming Language :: Python :: 3.8
Classifier: Programming Language :: Python :: 3.9
Classifier: Programming Language :: Python :: 3.10
Classifier: Programming Language :: Python :: 3.11
Classifier: License :: OSI Approved :: MIT License
Classifier: Operating System :: OS Independent
Requires-Python: >=3.8
License-File: LICENSE
Requires-Dist: requests >=2.25.0
Requires-Dist: websocket-client >=1.2.0
Requires-Dist: psutil >=5.8.0
Requires-Dist: pydantic >=1.9.0
Requires-Dist: tqdm >=4.62.0
